imio.webspellchecker-1.2-py3.12-nspkg.pth
imio/webspellchecker/__init__.py
imio/webspellchecker/config.py
imio/webspellchecker/configure.zcml
imio/webspellchecker/interfaces.py
imio/webspellchecker/profiles.zcml
imio/webspellchecker/setuphandlers.py
imio/webspellchecker/testing.py
imio/webspellchecker/testing.zcml
imio/webspellchecker/upgrades.py
imio/webspellchecker/upgrades.zcml
imio/webspellchecker/vocabularies.py
imio/webspellchecker/browser/__init__.py
imio/webspellchecker/browser/configure.zcml
imio/webspellchecker/browser/controlpanel.py
imio/webspellchecker/browser/viewlet.py
imio/webspellchecker/browser/webspellchecker.py
imio/webspellchecker/browser/static/controlpanel-icon.png
imio/webspellchecker/browser/static/p4-controlpanel-icon.png
imio/webspellchecker/browser/static/plone_spinner.svg
imio/webspellchecker/browser/static/wsctheme.css
imio/webspellchecker/locales/README.rst
imio/webspellchecker/locales/__init__.py
imio/webspellchecker/locales/imio.webspellchecker.pot
imio/webspellchecker/locales/update.py
imio/webspellchecker/locales/update.sh
imio/webspellchecker/locales/en/LC_MESSAGES/imio.webspellchecker.po
imio/webspellchecker/locales/fr/LC_MESSAGES/imio.webspellchecker.po
imio/webspellchecker/profiles/base/browserlayer.xml
imio/webspellchecker/profiles/base/registry.xml
imio/webspellchecker/profiles/plone4/controlpanel.xml
imio/webspellchecker/profiles/plone4/cssregistry.xml
imio/webspellchecker/profiles/plone4/metadata.xml
imio/webspellchecker/profiles/plone4/registry.xml
imio/webspellchecker/profiles/plone6/controlpanel.xml
imio/webspellchecker/profiles/plone6/metadata.xml
imio/webspellchecker/profiles/plone6/registry.xml
imio/webspellchecker/profiles/testing/metadata.xml
imio/webspellchecker/profiles/testing/registry.xml
imio/webspellchecker/profiles/uninstall/browserlayer.xml
imio/webspellchecker/tests/__init__.py
imio/webspellchecker/tests/test_setup.py
imio/webspellchecker/tests/test_view.py
imio_webspellchecker-1.2.dist-info/licenses/LICENSE.GPL
imio_webspellchecker-1.2.dist-info/licenses/LICENSE.md
imio_webspellchecker-1.2.dist-info/METADATA
imio_webspellchecker-1.2.dist-info/WHEEL
imio_webspellchecker-1.2.dist-info/entry_points.txt
imio_webspellchecker-1.2.dist-info/namespace_packages.txt
imio_webspellchecker-1.2.dist-info/top_level.txt
imio_webspellchecker-1.2.dist-info/RECORD
