Metadata-Version: 2.4
Name: imio.webspellchecker
Version: 1.2
Summary: Integration of Webspellchecker's WProofReader with Plone, providing real-time spellchecking for various WYSIWYG editors.
Home-page: https://github.com/collective/imio.webspellchecker
Author: iMio
Author-email: antoine.duchene@imio.be
License: GPL version 2
Project-URL: PyPI, https://pypi.python.org/pypi/imio.webspellchecker
Project-URL: Source, https://github.com/imio/imio.webspellchecker
Project-URL: Tracker, https://github.com/imio/imio.webspellchecker/issues
Keywords: Python Plone
Classifier: Environment :: Web Environment
Classifier: Framework :: Plone
Classifier: Framework :: Plone :: Addon
Classifier: Framework :: Plone :: 4.3
Classifier: Framework :: Plone :: 5.2
Classifier: Framework :: Plone :: 6.0
Classifier: Programming Language :: Python
Classifier: Programming Language :: Python :: 2.7
Classifier: Programming Language :: Python :: 3.8
Classifier: Programming Language :: Python :: 3.10
Classifier: Operating System :: OS Independent
Classifier: License :: OSI Approved :: GNU General Public License v2 (GPLv2)
License-File: LICENSE.GPL
License-File: LICENSE.md
Requires-Dist: setuptools
Requires-Dist: Products.CMFPlone>=4.3.19
Requires-Dist: Products.GenericSetup>=1.8.2
Requires-Dist: plone.api
Requires-Dist: six
Provides-Extra: test
Requires-Dist: plone.app.robotframework; extra == "test"
Requires-Dist: plone.app.testing; extra == "test"
Dynamic: author
Dynamic: author-email
Dynamic: classifier
Dynamic: description
Dynamic: description-content-type
Dynamic: home-page
Dynamic: keywords
Dynamic: license
Dynamic: license-file
Dynamic: project-url
Dynamic: provides-extra
Dynamic: requires-dist
Dynamic: summary
